{"cameraMode":{"drawMode":0,"name":"Shaded","section":"Shading Mode"},"sceneLighting":true,"audioPlay":false,"sceneViewState":{"m_AlwaysRefresh":false,"showFog":true,"showSkybox":true,"showFlares":true,"showImageEffects":true,"showParticleSystems":true,"showVisualEffectGraphs":true,"m_FxEnabled":true},"in2DMode":false,"pivot":{"x":981.0741577148438,"y":462.34991455078127,"z":313.56005859375},"rotation":{"x":0.07132817804813385,"y":-0.016457462683320047,"z":0.0011770074488595129,"w":0.9973196983337402},"size":578.862060546875,"orthographic":false}